pysphinx/__init__.py
pysphinx/const.py
pysphinx/crypto.py
pysphinx/node.py
pysphinx/payload.py
pysphinx/sphinx.py
pysphinx/utils.py
pysphinx/header/__init__.py
pysphinx/header/header.py
pysphinx/header/keys.py
pysphinx/header/mac.py
pysphinx/header/routing.py
pysphinx-0.0.5.dist-info/METADATA
pysphinx-0.0.5.dist-info/WHEEL
pysphinx-0.0.5.dist-info/licenses/LICENSE
pysphinx-0.0.5.dist-info/RECORD
