Metadata-Version: 2.3
Name: pysphinx
Version: 0.0.5
Summary: Sphinx packet implementation for mix networks
Project-URL: Homepage, https://github.com/youngjoon-lee/pysphinx
Project-URL: Issues, https://github.com/youngjoon-lee/pysphinx/issues
Author-email: Youngjoon Lee <taxihighway@gmail.com>
Maintainer-email: Youngjoon Lee <taxihighway@gmail.com>
License:                                  Apache License
License-File: LICENSE
Classifier: License :: OSI Approved :: Apache Software License
Classifier: Operating System :: OS Independent
Classifier: Programming Language :: Python :: 3
Classifier: Programming Language :: Python :: 3 :: Only
Classifier: Programming Language :: Python :: 3.10
Classifier: Programming Language :: Python :: 3.11
Classifier: Programming Language :: Python :: 3.12
Requires-Python: >=3.10
Requires-Dist: cryptography==41.0.7
